{
    "task_run_id": "135945ad-7b01-4578-93ff-eb8ae9cb5fd2",
    "workflow": {
        "id": "4ce58ec6-9cfc-4109-80a6-1ceea0d41b90",
        "name": "Error"
    },
    "started_at": 1771592905.6712441,
    "status": "success",
    "nodes": [
        {
            "node_id": "14fb5af0-4427-4c82-8d98-c1a7ef99184a",
            "label": "Delay 3s",
            "node_type": "delay",
            "program": null,
            "started_at": 1771592905.677352,
            "status": "success",
            "actions": [
                {
                    "action_id": "1b059edf-1ed6-4f8e-ab7b-9a6e358bcb62",
                    "type": "wait",
                    "payload": "{\"id\":\"14fb5af0-4427-4c82-8d98-c1a7ef99184a\",\"slug\":\"delay-3s-2\",\"created_at\":\"2026-02-20T02:00:00.339013Z\",\"updated_at\":\"2026-02-20T02:00:00.339025Z\",\"node_type\":\"delay\",\"label\":\"Delay 3s\",\"position_x\":676,\"position_y\":425,\"config\":{},\"created_by\":\"a35fe66e-bcb9-42a5-8906-4e8def6346f9\",\"workflow\":\"4ce58ec6-9cfc-4109-80a6-1ceea0d41b90\",\"program\":null,\"element\":null}",
                    "started_at": 1771592905.6814592,
                    "finished_at": 1771592907.7565014,
                    "status": "ok",
                    "error": null
                }
            ],
            "finished_at": 1771592907.7565086
        },
        {
            "node_id": "68caa12d-4412-4487-afeb-09039ec08767",
            "label": "Ignatius Mathews",
            "node_type": "program",
            "program": {
                "id": "bea989ee-b4b4-4963-bcdb-500e0d5de06f",
                "name": "Ignatius Mathews",
                "executable_path": "Velit qui similique"
            },
            "started_at": 1771592907.756517,
            "status": "failed",
            "actions": [
                {
                    "action_id": "3ee29149-b03a-460c-b041-9a192f92fb21",
                    "type": "open_program",
                    "payload": "{\"id\":\"68caa12d-4412-4487-afeb-09039ec08767\",\"program_name\":\"Ignatius Mathews\",\"slug\":\"ignatius-mathews\",\"created_at\":\"2026-02-20T02:00:05.328391Z\",\"updated_at\":\"2026-02-20T02:00:05.328402Z\",\"node_type\":\"program\",\"label\":\"Ignatius Mathews\",\"position_x\":581,\"position_y\":347,\"config\":{},\"created_by\":\"a35fe66e-bcb9-42a5-8906-4e8def6346f9\",\"workflow\":\"4ce58ec6-9cfc-4109-80a6-1ceea0d41b90\",\"program\":\"bea989ee-b4b4-4963-bcdb-500e0d5de06f\",\"element\":null}",
                    "started_at": 1771592907.761768,
                    "finished_at": 1771592908.047732,
                    "status": "error",
                    "error": "[WinError 2] The system cannot find the file specified: 'Velit qui similique'"
                }
            ],
            "finished_at": 1771592908.0477357
        }
    ],
    "finished_at": 1771592908.0477378
}